{"number":"441","name":"페라페","imageUrl":"https://pokedex.alansantos.dev/assets/pokemons/images/441.png","thumbnailUrl":"https://pokedex.alansantos.dev/assets/pokemons/thumbs/441.png","sprites":{"mainSpriteUrl":"https://pokedex.alansantos.dev/assets/pokemons/sprites/441/441_main.png","frontAnimatedSpriteUrl":"https://pokedex.alansantos.dev/assets/pokemons/sprites/441/441_front_animated.gif","backAnimatedSpriteUrl":"https://pokedex.alansantos.dev/assets/pokemons/sprites/441/441_back_animated.gif","frontShinyAnimatedSpriteUrl":"https://pokedex.alansantos.dev/assets/pokemons/sprites/441/441_front_shiny_animated.gif","backShinyAnimatedSpriteUrl":"https://pokedex.alansantos.dev/assets/pokemons/sprites/441/441_back_shiny_animated.gif"},"types":["Normal","Flying"],"weaknesses":["Electric","Ice","Rock"],
"descriptions":["사람의 말을 배우고 말할 수 있습니다. 모이면 다 같은 말을 배웁니다.","다른 포켓몬의 울음소리를 흉내내어 자기들 중 하나라고 착각하게 만듭니다. 이렇게 하면 공격하지 않습니다."],
"specie":"음표","height":"1.9 kg (4.2 lbs)","weight":"0.5 m (1′08″)","breeding":{
"egg":{"groups":["비행"],"cycle":"20 (4,884–5,140 걸음)"},"genders":[{"type":"MALE","percentage":"50%"},{"type":"FEMALE","percentage":"50%"}]},
"training":{"evYield":"1 공격","catchRate":"30 (3.9% 포켓볼과 함께,풀 HP)","baseFriendship":"35 (보통보다 낮음)","baseExp":"144",
"growthRate":"중간 느림"},"abilities":[{"name":"날카로운눈","description":"명중률이 떨어지지 않는다."},{"name":"갈지자걸음","description":"Raises evasiveness if the Pokémon is confused."}],"typesEffectiveness":{"Normal":"1","Fire":"1","Water":"1","Electric":"2","Grass":"½","Ice":"2","Fighting":"1","Poison":"1","Ground":"0","Flying":"1","Psychic":"1","Bug":"½","Rock":"2","Ghost":"0","Dragon":"1","Dark":"1","Steel":"1","Fairy":"1"},"evolutionChain":[{"number":"441","name":"페라페","imageUrl":"https://pokedex.alansantos.dev/assets/pokemons/images/441.png","thumbUrl":"https://pokedex.alansantos.dev/assets/pokemons/thumbs/441.png","type":"FIRST"}],"previousEvolutions":[],"nextEvolutions":[],"superEvolutions":[],"baseStats":{"hp":76,"attack":65,"defense":45,"spAtk":92,"spDef":42,"speed":91,"total":411},"cards":[{"number":"139","name":"페라페","expansionName":"Vivid Voltage","imageUrl":"https://pokedex.alansantos.dev/assets/pokemons/cards/441/SWSH4_EN_139.png"},{"number":"142","name":"페라페","expansionName":"Rebel Clash","imageUrl":"https://pokedex.alansantos.dev/assets/pokemons/cards/441/SWSH2_EN_142.png"},{"number":"162","name":"페라페","expansionName":"Unbroken Bonds","imageUrl":"https://pokedex.alansantos.dev/assets/pokemons/cards/441/SM10_EN_162.png"},{"number":"128","name":"페라페","expansionName":"XY–BREAKthrough","imageUrl":"https://pokedex.alansantos.dev/assets/pokemons/cards/441/XY8_EN_128.png"},{"number":"77","name":"페라페","expansionName":"Black & White—Plasma Blast","imageUrl":"https://pokedex.alansantos.dev/assets/pokemons/cards/441/BW10_EN_77.png"},{"number":"85","name":"페라페","expansionName":"Black & White—Dark Explorers","imageUrl":"https://pokedex.alansantos.dev/assets/pokemons/cards/441/BW5_EN_85.png"},{"number":"74","name":"페라페","expansionName":"Diamond & Pearl","imageUrl":"https://pokedex.alansantos.dev/assets/pokemons/cards/441/DP1_EN_74.png"},{"number":"55","name":"페라페","expansionName":"Diamond & Pearl—Majestic Dawn","imageUrl":"https://pokedex.alansantos.dev/assets/pokemons/cards/441/DP5_EN_55.png"},{"number":"54","name":"페라페 [G]","expansionName":"Platinum—Supreme Victors","imageUrl":"https://pokedex.alansantos.dev/assets/pokemons/cards/441/PL3_EN_54.png"},{"number":"95","name":"페라페","expansionName":"Platinum—Supreme Victors","imageUrl":"https://pokedex.alansantos.dev/assets/pokemons/cards/441/PL3_EN_95.png"}],
"soundUrl":"https://pokedex.alansantos.dev/assets/pokemons/sounds/441.mp3","moves":{
"levelUp":[{"level":1,"category":"특수","move":"수다","type":"Flying","power":"65","accuracy":"100"}
,{"level":1,"category":"변화","move":"비밀이야기","type":"Normal","power":"—","accuracy":"—"}
,{"level":1,"category":"특수","move":"하이퍼보이스","type":"Normal","power":"90","accuracy":"100"}
,{"level":1,"category":"물리","move":"쪼기","type":"Flying","power":"35","accuracy":"100"}
,{"level":1,"category":"변화","move":"도발","type":"Dark","power":"—","accuracy":"100"}
,{"level":5,"category":"변화","move":"울음소리","type":"Normal","power":"—","accuracy":"100"}
,{"level":9,"category":"변화","move":"따라하기","type":"Flying","power":"—","accuracy":"—"}
,{"level":13,"category":"변화","move":"노래하기","type":"Normal","power":"—","accuracy":"55"}
,{"level":17,"category":"물리","move":"마구찌르기","type":"Normal","power":"15","accuracy":"85"}
,{"level":21,"category":"특수","move":"수다","type":"Flying","power":"65","accuracy":"100"}
,{"level":25,"category":"변화","move":"도발","type":"Dark","power":"—","accuracy":"100"}
,{"level":29,"category":"특수","move":"돌림노래","type":"Normal","power":"60","accuracy":"100"}
,{"level":33,"category":"변화","move":"흉내내기","type":"Normal","power":"—","accuracy":"—"}
,{"level":37,"category":"특수","move":"에코보이스","type":"Normal","power":"40","accuracy":"100"}
,{"level":41,"category":"변화","move":"날개쉬기","type":"Flying","power":"—","accuracy":"—"}
,{"level":45,"category":"특수","move":"소란피기","type":"Normal","power":"90","accuracy":"100"}
,{"level":49,"category":"특수","move":"싱크로노이즈","type":"Psychic","power":"120","accuracy":"100"}
,{"level":50,"category":"변화","move":"깃털댄스","type":"Flying","power":"—","accuracy":"100"}
,{"level":57,"category":"특수","move":"하이퍼보이스","type":"Normal","power":"90","accuracy":"100"}]
,"technicalMachine":[{"technicalMachine":1,"category":"변화","move":"분발","type":"Normal","power":"—","accuracy":"—"}
,{"technicalMachine":6,"category":"변화","move":"맹독","type":"Poison","power":"—","accuracy":"90"}
,{"technicalMachine":10,"category":"특수","move":"잠재파워","type":"Normal","power":"60","accuracy":"100"}
,{"technicalMachine":11,"category":"변화","move":"쾌청","type":"Fire","power":"—","accuracy":"—"}
,{"technicalMachine":12,"category":"변화","move":"도발","type":"Dark","power":"—","accuracy":"100"}
,{"technicalMachine":17,"category":"변화","move":"방어","type":"Normal","power":"—","accuracy":"—"}
,{"technicalMachine":18,"category":"변화","move":"비바라기","type":"Water","power":"—","accuracy":"—"}
,{"technicalMachine":19,"category":"변화","move":"날개쉬기","type":"Flying","power":"—","accuracy":"—"}
,{"technicalMachine":21,"category":"물리","move":"화풀이","type":"Normal","power":"—","accuracy":"100"}
,{"technicalMachine":27,"category":"물리","move":"은혜갚기","type":"Normal","power":"—","accuracy":"100"}
,{"technicalMachine":32,"category":"변화","move":"그림자분신","type":"Normal","power":"—","accuracy":"—"}
,{"technicalMachine":40,"category":"물리","move":"제비반환","type":"Flying","power":"60","accuracy":"∞"}
,{"technicalMachine":41,"category":"변화","move":"트집","type":"Dark","power":"—","accuracy":"100"}
,{"technicalMachine":42,"category":"물리","move":"객기","type":"Normal","power":"70","accuracy":"100"}
,{"technicalMachine":44,"category":"변화","move":"잠자기","type":"Psychic","power":"—","accuracy":"—"}
,{"technicalMachine":45,"category":"변화","move":"헤롱헤롱","type":"Normal","power":"—","accuracy":"100"}
,{"technicalMachine":46,"category":"물리","move":"도둑질","type":"Dark","power":"60","accuracy":"100"}
,{"technicalMachine":48,"category":"특수","move":"돌림노래","type":"Normal","power":"60","accuracy":"100"}
,{"technicalMachine":49,"category":"특수","move":"에코보이스","type":"Normal","power":"40","accuracy":"100"}
,{"technicalMachine":51,"category":"물리","move":"강철날개","type":"Steel","power":"70","accuracy":"90"}
,{"technicalMachine":76,"category":"물리","move":"공중날기","type":"Flying","power":"90","accuracy":"95"}
,{"technicalMachine":87,"category":"변화","move":"뽐내기","type":"Normal","power":"—","accuracy":"85"}
,{"technicalMachine":88,"category":"변화","move":"잠꼬대","type":"Normal","power":"—","accuracy":"—"}
,{"technicalMachine":89,"category":"물리","move":"유턴","type":"Bug","power":"70","accuracy":"100"}
,{"technicalMachine":90,"category":"변화","move":"대타출동","type":"Normal","power":"—","accuracy":"—"}
,{"technicalMachine":100,"category":"변화","move":"비밀이야기","type":"Normal","power":"—","accuracy":"—"}],"technicalRecords":[]
,"egg":[{"category":"변화","move":"고속이동","type":"Psychic","power":"—","accuracy":"—"}
,{"category":"특수","move":"에어컷터","type":"Flying","power":"60","accuracy":"95"}
,{"category":"특수","move":"폭음파","type":"Normal","power":"140","accuracy":"100"}
,{"category":"변화","move":"안개제거","type":"Flying","power":"—","accuracy":"—"}
,{"category":"변화","move":"앵콜","type":"Normal","power":"—","accuracy":"100"}
,{"category":"변화","move":"나쁜음모","type":"Dark","power":"—","accuracy":"—"}
,{"category":"특수","move":"나이트헤드","type":"Ghost","power":"—","accuracy":"100"}
,{"category":"변화","move":"잠꼬대","type":"Normal","power":"—","accuracy":"—"}
,{"category":"물리","move":"강철날개","type":"Steel","power":"70","accuracy":"90"}
,{"category":"변화","move":"초음파","type":"Normal","power":"—","accuracy":"55"}]
,"tutor":[{"category":"변화","move":"안개제거","type":"Flying","power":"—","accuracy":"—"}
,{"category":"특수","move":"열풍","type":"Fire","power":"95","accuracy":"90"}
,{"category":"특수","move":"하이퍼보이스","type":"Normal","power":"90","accuracy":"100"}
,{"category":"변화","move":"역할","type":"Psychic","power":"—","accuracy":"—"}
,{"category":"물리","move":"불새","type":"Flying","power":"140","accuracy":"90"}
,{"category":"특수","move":"코골기","type":"Normal","power":"50","accuracy":"100"}
,{"category":"변화","move":"순풍","type":"Flying","power":"—","accuracy":"—"}
,{"category":"특수","move":"소란피기","type":"Normal","power":"90","accuracy":"100"}]
,"evolution":[],"preEvolution":[]},"generation":"GENERATION_IV"}