{"number":"530","name":"몰드류","imageUrl":"https://pokedex.alansantos.dev/assets/pokemons/images/530.png","thumbnailUrl":"https://pokedex.alansantos.dev/assets/pokemons/thumbs/530.png","sprites":{"mainSpriteUrl":"https://pokedex.alansantos.dev/assets/pokemons/sprites/530/530_main.png","frontAnimatedSpriteUrl":"https://pokedex.alansantos.dev/assets/pokemons/sprites/530/530_front_animated.gif","backAnimatedSpriteUrl":"https://pokedex.alansantos.dev/assets/pokemons/sprites/530/530_back_animated.gif","frontShinyAnimatedSpriteUrl":"https://pokedex.alansantos.dev/assets/pokemons/sprites/530/530_front_shiny_animated.gif","backShinyAnimatedSpriteUrl":"https://pokedex.alansantos.dev/assets/pokemons/sprites/530/530_back_shiny_animated.gif"},"types":["Ground","Steel"],"weaknesses":["Fire","Water","Fighting","Ground"],
"descriptions":["드릴 킹으로 알려진 이 포켓몬은 시속 90마일 이상의 속도로 터널을 뚫을 수 있습니다.","자연적으로 형성된 것처럼 보이는 터널이 실제로는 몰드류의 만연한 굴착의 결과인 경우가 많습니다."],
"specie":"땅밑","height":"40.4 kg (89.1 lbs)","weight":"0.7 m (2′04″)","breeding":{
"egg":{"groups":["육상"],"cycle":"20 (4,884–5,140 걸음)"},"genders":[{"type":"MALE","percentage":"50%"},{"type":"FEMALE","percentage":"50%"}]},
"training":{"evYield":"2 공격","catchRate":"60 (7.8% 포켓볼과 함께,풀 HP)","baseFriendship":"50 (노말)","baseExp":"178",
"growthRate":"중간 빠름"},"abilities":[{"name":"모래헤치기","description":"Boosts the Pokémon's Speed stat in a sandstorm."},{"name":"모래의힘","description":"Boosts the power of Rock-, Ground-, and Steel-type moves in a sandstorm."}],"typesEffectiveness":{"Normal":"½","Fire":"2","Water":"2","Electric":"0","Grass":"1","Ice":"1","Fighting":"2","Poison":"0","Ground":"2","Flying":"½","Psychic":"½","Bug":"½","Rock":"¼","Ghost":"1","Dragon":"½","Dark":"1","Steel":"½","Fairy":"½"},"evolutionChain":[{"number":"529","name":"두더류","imageUrl":"https://pokedex.alansantos.dev/assets/pokemons/images/529.png","thumbUrl":"https://pokedex.alansantos.dev/assets/pokemons/thumbs/529.png","type":"FIRST"},{"number":"530","name":"몰드류","imageUrl":"https://pokedex.alansantos.dev/assets/pokemons/images/530.png","thumbUrl":"https://pokedex.alansantos.dev/assets/pokemons/thumbs/530.png","type":"LAST",
"requirement":"Level 31"}],"previousEvolutions":[{"number":"529","name":"두더류","imageUrl":"https://pokedex.alansantos.dev/assets/pokemons/images/529.png","thumbUrl":"https://pokedex.alansantos.dev/assets/pokemons/thumbs/529.png","type":"FIRST"}],"nextEvolutions":[],"superEvolutions":[],"baseStats":{"hp":110,"attack":135,"defense":60,"spAtk":50,"spDef":65,"speed":88,"total":508},"cards":[{"number":"122","name":"몰드류","expansionName":"Vivid Voltage","imageUrl":"https://pokedex.alansantos.dev/assets/pokemons/cards/530/SWSH4_EN_122.png"},{"number":"115","name":"몰드류","expansionName":"Cosmic Eclipse","imageUrl":"https://pokedex.alansantos.dev/assets/pokemons/cards/530/SM12_EN_115.png"},{"number":"246","name":"몰드류","expansionName":"Cosmic Eclipse","imageUrl":"https://pokedex.alansantos.dev/assets/pokemons/cards/530/SM12_EN_246.png"},{"number":"119","name":"몰드류","expansionName":"Unified Minds","imageUrl":"https://pokedex.alansantos.dev/assets/pokemons/cards/530/SM11_EN_119.png"},{"number":"96","name":"몰드류","expansionName":"XY—Primal Clash","imageUrl":"https://pokedex.alansantos.dev/assets/pokemons/cards/530/XY5_EN_96.png"},{"number":"97","name":"몰드류","expansionName":"XY—Primal Clash","imageUrl":"https://pokedex.alansantos.dev/assets/pokemons/cards/530/XY5_EN_97.png"},{"number":"82","name":"몰드류-EX","expansionName":"Black & White—Legendary Treasures","imageUrl":"https://pokedex.alansantos.dev/assets/pokemons/cards/530/BW11_EN_82.png"},{"number":"56","name":"몰드류","expansionName":"Black & White—Dark Explorers","imageUrl":"https://pokedex.alansantos.dev/assets/pokemons/cards/530/BW5_EN_56.png"},{"number":"57","name":"몰드류","expansionName":"Black & White—Dark Explorers","imageUrl":"https://pokedex.alansantos.dev/assets/pokemons/cards/530/BW5_EN_57.png"},{"number":"56","name":"몰드류","expansionName":"Black & White—Emerging Powers","imageUrl":"https://pokedex.alansantos.dev/assets/pokemons/cards/530/BW2_EN_56.png"}],
"soundUrl":"https://pokedex.alansantos.dev/assets/pokemons/sounds/530.mp3","moves":{
"levelUp":[{"level":1,"category":"변화","move":"손톱갈기","type":"Dark","power":"—","accuracy":"—"}
,{"level":1,"category":"물리","move":"뿔드릴","type":"Normal","power":"—","accuracy":"30"}
,{"level":1,"category":"특수","move":"진흙뿌리기","type":"Ground","power":"20","accuracy":"100"}
,{"level":1,"category":"물리","move":"고속스핀","type":"Normal","power":"50","accuracy":"100"}
,{"level":1,"category":"물리","move":"할퀴기","type":"Normal","power":"40","accuracy":"100"}
,{"level":12,"category":"물리","move":"마구할퀴기","type":"Normal","power":"18","accuracy":"80"}
,{"level":16,"category":"물리","move":"메탈크로우","type":"Steel","power":"50","accuracy":"95"}
,{"level":20,"category":"변화","move":"모래바람","type":"Rock","power":"—","accuracy":"—"}
,{"level":24,"category":"물리","move":"브레이크크루","type":"Normal","power":"75","accuracy":"95"}
,{"level":28,"category":"물리","move":"스톤샤워","type":"Rock","power":"75","accuracy":"90"}
,{"level":34,"category":"물리","move":"구멍파기","type":"Ground","power":"80","accuracy":"100"}
,{"level":40,"category":"변화","move":"칼춤","type":"Normal","power":"—","accuracy":"—"}
,{"level":46,"category":"물리","move":"드릴라이너","type":"Ground","power":"80","accuracy":"95"}
,{"level":52,"category":"물리","move":"지진","type":"Ground","power":"100","accuracy":"100"}
,{"level":58,"category":"물리","move":"땅가르기","type":"Ground","power":"—","accuracy":"30"}]
,"technicalMachine":[{"technicalMachine":8,"category":"특수","move":"파괴광선","type":"Normal","power":"150","accuracy":"90"}
,{"technicalMachine":9,"category":"물리","move":"기가임팩트","type":"Normal","power":"150","accuracy":"90"}
,{"technicalMachine":15,"category":"물리","move":"구멍파기","type":"Ground","power":"80","accuracy":"100"}
,{"technicalMachine":21,"category":"변화","move":"잠자기","type":"Psychic","power":"—","accuracy":"—"}
,{"technicalMachine":22,"category":"물리","move":"스톤샤워","type":"Rock","power":"75","accuracy":"90"}
,{"technicalMachine":24,"category":"특수","move":"코골기","type":"Normal","power":"50","accuracy":"100"}
,{"technicalMachine":25,"category":"변화","move":"방어","type":"Normal","power":"—","accuracy":"—"}
,{"technicalMachine":31,"category":"변화","move":"헤롱헤롱","type":"Normal","power":"—","accuracy":"100"}
,{"technicalMachine":32,"category":"변화","move":"모래바람","type":"Rock","power":"—","accuracy":"—"}
,{"technicalMachine":39,"category":"물리","move":"객기","type":"Normal","power":"70","accuracy":"100"}
,{"technicalMachine":43,"category":"물리","move":"깨트리다","type":"Fighting","power":"75","accuracy":"100"}
,{"technicalMachine":48,"category":"물리","move":"암석봉인","type":"Rock","power":"60","accuracy":"95"}
,{"technicalMachine":49,"category":"물리","move":"모래지옥","type":"Ground","power":"35","accuracy":"85"}
,{"technicalMachine":53,"category":"특수","move":"머드숏","type":"Ground","power":"55","accuracy":"95"}
,{"technicalMachine":54,"category":"물리","move":"락블레스트","type":"Rock","power":"25","accuracy":"90"}
,{"technicalMachine":59,"category":"물리","move":"내던지기","type":"Dark","power":"—","accuracy":"100"}
,{"technicalMachine":65,"category":"물리","move":"섀도크루","type":"Ghost","power":"70","accuracy":"100"}
,{"technicalMachine":76,"category":"특수","move":"돌림노래","type":"Normal","power":"60","accuracy":"100"}
,{"technicalMachine":81,"category":"물리","move":"땅고르기","type":"Ground","power":"60","accuracy":"100"}
,{"technicalMachine":96,"category":"물리","move":"스마트호른","type":"Steel","power":"70","accuracy":"—"}
,{"technicalMachine":97,"category":"물리","move":"세차게휘두르기","type":"Dark","power":"60","accuracy":"100"}
,{"technicalMachine":98,"category":"물리","move":"분함의발구르기","type":"Ground","power":"75","accuracy":"100"}],"technicalRecords":[
{"technicalRecord":0,"category":"변화","move":"칼춤","type":"Normal","power":"—","accuracy":"—"},
{"technicalRecord":10,"category":"물리","move":"지진","type":"Ground","power":"100","accuracy":"100"},
{"technicalRecord":20,"category":"변화","move":"대타출동","type":"Normal","power":"—","accuracy":"—"},
{"technicalRecord":22,"category":"특수","move":"오물폭탄","type":"Poison","power":"90","accuracy":"100"},
{"technicalRecord":26,"category":"변화","move":"버티기","type":"Normal","power":"—","accuracy":"—"},
{"technicalRecord":27,"category":"변화","move":"잠꼬대","type":"Normal","power":"—","accuracy":"—"},
{"technicalRecord":46,"category":"변화","move":"철벽","type":"Steel","power":"—","accuracy":"—"},
{"technicalRecord":57,"category":"물리","move":"독찌르기","type":"Poison","power":"80","accuracy":"100"},
{"technicalRecord":60,"category":"물리","move":"시저크로스","type":"Bug","power":"80","accuracy":"100"},
{"technicalRecord":64,"category":"특수","move":"기합구슬","type":"Fighting","power":"120","accuracy":"70"},
{"technicalRecord":67,"category":"특수","move":"대지의힘","type":"Ground","power":"90","accuracy":"100"},
{"technicalRecord":74,"category":"물리","move":"아이언헤드","type":"Steel","power":"80","accuracy":"100"},
{"technicalRecord":76,"category":"변화","move":"스텔스록","type":"Rock","power":"—","accuracy":"—"},
{"technicalRecord":87,"category":"물리","move":"드릴라이너","type":"Ground","power":"80","accuracy":"95"},
{"technicalRecord":94,"category":"물리","move":"10만마력","type":"Ground","power":"95","accuracy":"95"}]
,"egg":[{"category":"변화","move":"금속음","type":"Steel","power":"—","accuracy":"85"}
,{"category":"물리","move":"베어가르기","type":"Normal","power":"70","accuracy":"100"}
,{"category":"물리","move":"지옥의바퀴","type":"Fighting","power":"80","accuracy":"80"}]
,"tutor":[{"category":"특수","move":"열사의대지","type":"Ground","power":"70","accuracy":"100"}]
,"evolution":[{"category":"물리","move":"뿔드릴","type":"Normal","power":"—","accuracy":"30"}],"preEvolution":[]},"generation":"GENERATION_V"}