{"number":"590","name":"깜놀버슬","imageUrl":"https://pokedex.alansantos.dev/assets/pokemons/images/590.png","thumbnailUrl":"https://pokedex.alansantos.dev/assets/pokemons/thumbs/590.png","sprites":{"mainSpriteUrl":"https://pokedex.alansantos.dev/assets/pokemons/sprites/590/590_main.png","frontAnimatedSpriteUrl":"https://pokedex.alansantos.dev/assets/pokemons/sprites/590/590_front_animated.gif","backAnimatedSpriteUrl":"https://pokedex.alansantos.dev/assets/pokemons/sprites/590/590_back_animated.gif","frontShinyAnimatedSpriteUrl":"https://pokedex.alansantos.dev/assets/pokemons/sprites/590/590_front_shiny_animated.gif","backShinyAnimatedSpriteUrl":"https://pokedex.alansantos.dev/assets/pokemons/sprites/590/590_back_shiny_animated.gif"},"types":["Grass","Poison"],"weaknesses":["Fire","Psychic","Flying","Ice"],
"descriptions":["이 포켓몬의 손에서 나오는 포자는 유독성이 높지만, 완전히 말리면 위장약으로 쓸 수 있습니다.","깜놀버슬의 포켓볼 모양이 무엇을 의미하는지, 왜 깜놀버슬이 있는지는 아무도 모릅니다."],
"specie":"버섯","height":"1.0 kg (2.2 lbs)","weight":"0.2 m (0′08″)","breeding":{
"egg":{"groups":["식물"],"cycle":"20 (4,884–5,140 걸음)"},"genders":[{"type":"MALE","percentage":"50%"},{"type":"FEMALE","percentage":"50%"}]},
"training":{"evYield":"1 HP","catchRate":"190 (24.8% 포켓볼과 함께,풀 HP)","baseFriendship":"50 (노말)","baseExp":"59",
"growthRate":"중간 빠름"},"abilities":[{"name":"포자","description":"스치면 독, 마비, 잠듦 상태가 될 때가 있다."}],"typesEffectiveness":{"Normal":"1","Fire":"2","Water":"½","Electric":"½","Grass":"¼","Ice":"2","Fighting":"½","Poison":"1","Ground":"1","Flying":"2","Psychic":"2","Bug":"1","Rock":"1","Ghost":"1","Dragon":"1","Dark":"1","Steel":"1","Fairy":"½"},"evolutionChain":[{"number":"590","name":"깜놀버슬","imageUrl":"https://pokedex.alansantos.dev/assets/pokemons/images/590.png","thumbUrl":"https://pokedex.alansantos.dev/assets/pokemons/thumbs/590.png","type":"FIRST"},{"number":"591","name":"뽀록나","imageUrl":"https://pokedex.alansantos.dev/assets/pokemons/images/591.png","thumbUrl":"https://pokedex.alansantos.dev/assets/pokemons/thumbs/591.png","type":"LAST","requirement":"Level 39"}],"previousEvolutions":[],"nextEvolutions":[{"number":"591","name":"뽀록나","imageUrl":"https://pokedex.alansantos.dev/assets/pokemons/images/591.png","thumbUrl":"https://pokedex.alansantos.dev/assets/pokemons/thumbs/591.png"
,"type":"LAST",
"requirement":"Level 39"}],"superEvolutions":[],"baseStats":{"hp":69,"attack":55,"defense":45,"spAtk":55,"spDef":55,"speed":15,"total":294},"cards":[{"number":"13","name":"깜놀버슬","expansionName":"Unified Minds","imageUrl":"https://pokedex.alansantos.dev/assets/pokemons/cards/590/SM11_EN_13.png"},{"number":"12","name":"깜놀버슬","expansionName":"XY—Steam Siege","imageUrl":"https://pokedex.alansantos.dev/assets/pokemons/cards/590/XY11_EN_12.png"},{"number":"12","name":"깜놀버슬","expansionName":"Black & White—Plasma Storm","imageUrl":"https://pokedex.alansantos.dev/assets/pokemons/cards/590/BW8_EN_12.png"},{"number":"17","name":"깜놀버슬","expansionName":"Black & White—Dragons Exalted","imageUrl":"https://pokedex.alansantos.dev/assets/pokemons/cards/590/BW6_EN_17.png"},{"number":"8","name":"깜놀버슬","expansionName":"Black & White—Next Destinies","imageUrl":"https://pokedex.alansantos.dev/assets/pokemons/cards/590/BW4_EN_8.png"},{"number":"9","name":"깜놀버슬","expansionName":"Black & White—Noble Victories","imageUrl":"https://pokedex.alansantos.dev/assets/pokemons/cards/590/BW3_EN_9.png"}],
"soundUrl":"https://pokedex.alansantos.dev/assets/pokemons/sounds/590.mp3","moves":{
"levelUp":[{"level":1,"category":"특수","move":"흡수","type":"Grass","power":"20","accuracy":"100"},{"level":1,"category":"물리","move":"놀래키기","type":"Ghost","power":"30","accuracy":"100"},{"level":4,"category":"변화","move":"성장","type":"Normal","power":"—","accuracy":"—"},{"level":8,"category":"변화","move":"저리가루","type":"Grass","power":"—","accuracy":"75"},{"level":12,"category":"특수","move":"메가드레인","type":"Grass","power":"40","accuracy":"100"},{"level":16,"category":"변화","move":"광합성","type":"Grass","power":"—","accuracy":"—"},{"level":20,"category":"특수","move":"클리어스모그","type":"Poison","power":"50","accuracy":"—"},{"level":24,"category":"변화","move":"달콤한향기","type":"Normal","power":"—","accuracy":"100"},{"level":28,"category":"특수","move":"기가드레인","type":"Grass","power":"75","accuracy":"100"},{"level":32,"category":"변화","move":"뿌리박기","type":"Grass","power":"—","accuracy":"—"},{"level":36,"category":"변화","move":"맹독","type":"Poison","power":"—","accuracy":"90"},{"level":40,"category":"변화","move":"분노가루","type":"Bug","power":"—","accuracy":"—"},{"level":44,"category":"특수","move":"솔라빔","type":"Grass","power":"120","accuracy":"100"},{"level":48,"category":"변화","move":"버섯포자","type":"Grass","power":"—","accuracy":"100"}],"technicalMachine":[{"technicalMachine":11,"category":"특수","move":"솔라빔","type":"Grass","power":"120","accuracy":"100"},{"technicalMachine":21,"category":"변화","move":"잠자기","type":"Psychic","power":"—","accuracy":"—"},{"technicalMachine":24,"category":"특수","move":"코골기","type":"Normal","power":"50","accuracy":"100"},{"technicalMachine":25,"category":"변화","move":"방어","type":"Normal","power":"—","accuracy":"—"},{"technicalMachine":28,"category":"특수","move":"기가드레인","type":"Grass","power":"75","accuracy":"100"},{"technicalMachine":31,"category":"변화","move":"헤롱헤롱","type":"Normal","power":"—","accuracy":"100"},{"technicalMachine":33,"category":"변화","move":"비바라기"
,"type":"Water","power":"—","accuracy":"—"}
,{"technicalMachine":34,"category":"변화","move":"쾌청"
,"type":"Fire","power":"—","accuracy":"—"}
,{"technicalMachine":39,"category":"물리","move":"객기"
,"type":"Normal","power":"70","accuracy":"100"}
,{"technicalMachine":57,"category":"물리","move":"보복"
,"type":"Dark","power":"50","accuracy":"100"}
,{"technicalMachine":74,"category":"특수","move":"베놈쇼크"
,"type":"Poison","power":"65","accuracy":"100"}
,{"technicalMachine":76,"category":"특수","move":"돌림노래"
,"type":"Normal","power":"60","accuracy":"100"}],"technicalRecords":[
{"technicalRecord":1,"category":"물리","move":"누르기"
,"type":"Normal","power":"85","accuracy":"100"},
{"technicalRecord":20,"category":"변화","move":"대타출동"
,"type":"Normal","power":"—","accuracy":"—"},
{"technicalRecord":22,"category":"특수","move":"오물폭탄"
,"type":"Poison","power":"90","accuracy":"100"},
{"technicalRecord":26,"category":"변화","move":"버티기"
,"type":"Normal","power":"—","accuracy":"—"},
{"technicalRecord":27,"category":"변화","move":"잠꼬대"
,"type":"Normal","power":"—","accuracy":"—"},
{"technicalRecord":59,"category":"물리","move":"씨폭탄"
,"type":"Grass","power":"80","accuracy":"100"},
{"technicalRecord":65,"category":"특수","move":"에너지볼"
,"type":"Grass","power":"90","accuracy":"100"},
{"technicalRecord":77,"category":"특수","move":"풀묶기"
,"type":"Grass","power":"—","accuracy":"100"},
{"technicalRecord":81,"category":"물리","move":"속임수"
,"type":"Dark","power":"95","accuracy":"100"},
{"technicalRecord":96,"category":"특수","move":"꽃가루경단"
,"type":"Bug","power":"90","accuracy":"100"}]
,"egg":[{"category":"변화","move":"웅크리기"
,"type":"Normal","power":"—","accuracy":"—"}
,{"category":"변화","move":"독가루"
,"type":"Poison","power":"—","accuracy":"75"}
,{"category":"물리","move":"구르기"
,"type":"Rock","power":"30","accuracy":"90"}
,{"category":"변화","move":"고민씨"
,"type":"Grass","power":"—","accuracy":"100"}]
,"tutor":[]
,"evolution":[],"preEvolution":[]},"generation":"GENERATION_V"}